pythonsdm/__init__.py
pythonsdm/sdm.py
pythonsdm-0.3.1.dist-info/entry_points.txt
pythonsdm-0.3.1.dist-info/WHEEL
pythonsdm-0.3.1.dist-info/METADATA
pythonsdm-0.3.1.dist-info/RECORD
