Metadata-Version: 2.1
Name: pythonsdm
Version: 0.3.1
Summary: Supervised Descent Method and its Applications to Face Alignment
Author: Gilad Kutiel
Author-email: gilad.kutiel@gmail.com
Requires-Python: >=3.8,<4.0
Classifier: Programming Language :: Python :: 3
Classifier: Programming Language :: Python :: 3.10
Classifier: Programming Language :: Python :: 3.8
Classifier: Programming Language :: Python :: 3.9
Requires-Dist: fire (>=0.4.0,<0.5.0)
Requires-Dist: numpy (>=1.22.1,<2.0.0)
Requires-Dist: scikit-image (>=0.19.1,<0.20.0)
Requires-Dist: scikit-learn (>=1.0.2,<2.0.0)
Requires-Dist: tqdm (>=4.62.3,<5.0.0)
